argparse_manpage_birdtools-1.7.0.data/data/LICENSE
argparse_manpage_birdtools-1.7.0.data/data/README.md
build_manpages/__init__.py
build_manpages/build_manpage.py
build_manpages/build_manpages.py
build_manpages/manpage.py
argparse_manpage_birdtools-1.7.0.dist-info/AUTHORS
argparse_manpage_birdtools-1.7.0.dist-info/LICENSE
argparse_manpage_birdtools-1.7.0.dist-info/METADATA
argparse_manpage_birdtools-1.7.0.dist-info/WHEEL
argparse_manpage_birdtools-1.7.0.dist-info/top_level.txt
argparse_manpage_birdtools-1.7.0.dist-info/RECORD
