Metadata-Version: 2.1
Name: argparse-manpage-birdtools
Version: 1.7.0
Summary: Format ROFF documents (manual page format) from python's ArgumentParser object.
Home-page: https://github.com/wwood/argparse-manpage-birdtools
Author: Ben Woodcroft, Gabriele Giammatteo, Pavel Raiskup
Author-email: benjwoodcroft@gmail.com, gabriele.giammatteo@eng.it, praiskup@redhat.com
Maintainer: Ben Woodcroft
Maintainer-email: benjwoodcroft@gmail.com
License: Apache 2.0
License-File: LICENSE
License-File: AUTHORS
